setup.py
./bin/chefpy
chefpy/__init__.py
chefpy/chefpy.py
chefpy.egg-info/PKG-INFO
chefpy.egg-info/SOURCES.txt
chefpy.egg-info/dependency_links.txt
chefpy.egg-info/not-zip-safe
chefpy.egg-info/requires.txt
chefpy.egg-info/top_level.txt