Metadata-Version: 1.0
Name: chefpy
Version: 0.321
Summary: Unofficial Codechef Api for user's status,rank,solutions etc.
Home-page: http://github.com/zuck007/chefpy
Author: Pradeep Khileri
Author-email: pradeepchoudhary009@gmail.com
License: MIT
Keywords: api codechef automation command-line linux web-scraping
Platform: UNKNOWN
